lab_14/src/01_mnist/01_HDL/03_sys_array_mnist_split/sys_array_split.sv
`ifndef types
`define types 0;
typedef struct packed {
  logic [9:0] A_W_0, A_L_0, A_W_1, A_L_1;
  logic [9:0] B_W_0, B_L_0, B_W_1, B_L_1;
  logic [9:0] O_W_0, O_L_0, O_W_1, O_L_1;
  logic [7:0] to_n1;
  logic [7:0] to_n2;
  logic signed [8:0] parent;
} split_type;
`endif

module sys_array_split #(
    parameter ARRAY_W = 10, //Максимальное число строк в систолическом массиве
    parameter ARRAY_L = 30, //Максимальное число столбцов в систолическом массиве 
    parameter ARRAY_MAX_A_W = 10,
    parameter OUT_SIZE = 64
) (
    input clk,
    input reset_n, 
    input start,
    input  [9:0]   ARRAY_W_W,
    input  [9:0]   ARRAY_W_L,
    input  [9:0]   ARRAY_A_W,
    input  [9:0]   ARRAY_A_L,

    output reg ready,
    
    output split_type out_data[OUT_SIZE],
    output reg [7:0] first_none,
    output reg [7:0] last
);

  reg [9:0] cnt, cur;

  always @(posedge clk) begin
    if (~reset_n) begin
      cnt <= 16'd0;
      cur <= 16'd0;
      ready <= 1'b0;
      last <= 16'd0;
      first_none <= 16'd0;
      out_data <= '{default:'0};
    end else if (start)  begin
      cnt <= 16'd0;
      cur <= 16'd0;
      ready <= 1'b0;
      first_none <= 16'd0;
      last <= 16'd0;
      out_data <= '{default:'0};
    end
    else
    begin
      if (cnt == 0) begin
        out_data[cnt].A_W_0 <= 'b0;
        out_data[cnt].A_L_0 <= 'b0;
        out_data[cnt].A_W_1 <= ARRAY_A_W - 1;
        out_data[cnt].A_L_1 <= ARRAY_A_L - 1;

        out_data[cnt].B_W_0 <= 'b0;
        out_data[cnt].B_L_0 <= 'b0;
        out_data[cnt].B_W_1 <= ARRAY_W_W - 1;
        out_data[cnt].B_L_1 <= ARRAY_W_L - 1;

        out_data[cnt].O_W_0 <= 'b0;
        out_data[cnt].O_L_0 <= 'b0;
        out_data[cnt].O_W_1 <= ARRAY_A_W - 1;
        out_data[cnt].O_L_1 <= ARRAY_W_L - 1;

        cur <= cnt;
        out_data[cnt].parent = -1;

        cnt <= cnt + 1;
      end else begin
        if (cur < cnt) begin
          //LEN_A_W <= (out_data[cur].A_W_1 - out_data[cur].A_W_0);
          //LEN_A_L <= (out_data[cur].A_L_1 - out_data[cur].A_L_0);
          //LEN_B_W <= (out_data[cur].B_W_1 - out_data[cur].B_W_0);
          //LEN_B_L <= (out_data[cur].B_L_1 - out_data[cur].B_L_0);
          if (!((((out_data[cur].A_L_1 - out_data[cur].A_L_0)) < ARRAY_L) && (((out_data[cur].A_W_1 - out_data[cur].A_W_0)) < ARRAY_MAX_A_W) && ((out_data[cur].B_L_1 - out_data[cur].B_L_0) < ARRAY_W)))
                begin
            if ((((out_data[cur].A_W_1 - out_data[cur].A_W_0)) >= ((out_data[cur].A_L_1 - out_data[cur].A_L_0))) && (((out_data[cur].A_W_1 - out_data[cur].A_W_0)) >= (out_data[cur].B_L_1 - out_data[cur].B_L_0))) begin

              out_data[cnt].A_W_0 <= out_data[cur].A_W_0;
              out_data[cnt].A_L_0 <= out_data[cur].A_L_0;
              out_data[cnt].A_W_1 <= out_data[cur].A_W_0 + (((out_data[cur].A_W_1 - out_data[cur].A_W_0) + 1) >> 1) - 1;
              out_data[cnt].A_L_1 <= out_data[cur].A_L_1;

              out_data[cnt].B_W_0 <= out_data[cur].B_W_0;
              out_data[cnt].B_L_0 <= out_data[cur].B_L_0;
              out_data[cnt].B_W_1 <= out_data[cur].B_W_1;
              out_data[cnt].B_L_1 <= out_data[cur].B_L_1;

              out_data[cnt].O_W_0 <= out_data[cur].O_W_0;
              out_data[cnt].O_L_0 <= out_data[cur].O_L_0;
              out_data[cnt].O_W_1 <= out_data[cur].O_W_0 + (((out_data[cur].A_W_1 - out_data[cur].A_W_0) + 1) >> 1) - 1;
              out_data[cnt].O_L_1 <= out_data[cur].O_L_1;

              out_data[cur].to_n1 <= cnt;

              out_data[cnt+1].A_W_0 <= out_data[cur].A_W_0 + (((out_data[cur].A_W_1 - out_data[cur].A_W_0) + 1) >> 1);
              out_data[cnt+1].A_L_0 <= out_data[cur].A_L_0;
              out_data[cnt+1].A_W_1 <= out_data[cur].A_W_1;
              out_data[cnt+1].A_L_1 <= out_data[cur].A_L_1;

              out_data[cnt+1].B_W_0 <= out_data[cur].B_W_0;
              out_data[cnt+1].B_L_0 <= out_data[cur].B_L_0;
              out_data[cnt+1].B_W_1 <= out_data[cur].B_W_1;
              out_data[cnt+1].B_L_1 <= out_data[cur].B_L_1;

              out_data[cnt+1].O_W_0 <= out_data[cur].O_W_0 + (((out_data[cur].A_W_1 - out_data[cur].A_W_0) + 1) >> 1);
              out_data[cnt+1].O_L_0 <= out_data[cur].O_L_0;
              out_data[cnt+1].O_W_1 <= out_data[cur].O_W_1;
              out_data[cnt+1].O_L_1 <= out_data[cur].O_L_1;

              out_data[cur].to_n2 <= cnt + 1;
              cnt <= cnt + 2;
            end else begin
              if (((out_data[cur].B_L_1 - out_data[cur].B_L_0) >= ((out_data[cur].A_L_1 - out_data[cur].A_L_0))) && ((out_data[cur].B_L_1 - out_data[cur].B_L_0) >= ((out_data[cur].A_W_1 - out_data[cur].A_W_0))))
                        begin

                out_data[cnt].A_W_0 <= out_data[cur].A_W_0;
                out_data[cnt].A_L_0 <= out_data[cur].A_L_0;
                out_data[cnt].A_W_1 <= out_data[cur].A_W_1;
                out_data[cnt].A_L_1 <= out_data[cur].A_L_1;

                out_data[cnt].B_W_0 <= out_data[cur].B_W_0;
                out_data[cnt].B_L_0 <= out_data[cur].B_L_0;
                out_data[cnt].B_W_1 <= out_data[cur].B_W_1;
                out_data[cnt].B_L_1 <= out_data[cur].B_L_0 + ((out_data[cur].B_L_1 - out_data[cur].B_L_0 + 1) >> 1) - 1;
                out_data[cur].to_n1 <= cnt;

                out_data[cnt].O_W_0 <= out_data[cur].O_W_0;
                out_data[cnt].O_L_0 <= out_data[cur].O_L_0;
                out_data[cnt].O_W_1 <= out_data[cur].O_W_1;
                out_data[cnt].O_L_1 <= out_data[cur].O_L_0 + ((out_data[cur].B_L_1 - out_data[cur].B_L_0 + 1) >> 1) - 1;



                out_data[cnt+1].A_W_0 <= out_data[cur].A_W_0;
                out_data[cnt+1].A_L_0 <= out_data[cur].A_L_0;
                out_data[cnt+1].A_W_1 <= out_data[cur].A_W_1;
                out_data[cnt+1].A_L_1 <= out_data[cur].A_L_1;

                out_data[cnt+1].B_W_0 <= out_data[cur].B_W_0;
                out_data[cnt+1].B_L_0 <= out_data[cur].B_L_0 + ((out_data[cur].B_L_1 - out_data[cur].B_L_0 + 1) >> 1);
                out_data[cnt+1].B_W_1 <= out_data[cur].B_W_1;
                out_data[cnt+1].B_L_1 <= out_data[cur].B_L_1;

                out_data[cnt+1].O_W_0 <= out_data[cur].O_W_0;
                out_data[cnt+1].O_L_0 <= out_data[cur].O_L_0 + ((out_data[cur].B_L_1 - out_data[cur].B_L_0 + 1) >> 1);
                out_data[cnt+1].O_W_1 <= out_data[cur].O_W_1;
                out_data[cnt+1].O_L_1 <= out_data[cur].O_L_1;

                out_data[cur].to_n2 <= cnt + 1;
                cnt <= cnt + 2;
              end else begin
                if ((((out_data[cur].A_L_1 - out_data[cur].A_L_0)) >= (out_data[cur].B_L_1 - out_data[cur].B_L_0)) && (((out_data[cur].A_L_1 - out_data[cur].A_L_0)) >= ((out_data[cur].A_W_1 - out_data[cur].A_W_0))))
                            begin

                  out_data[cnt].A_W_0 <= out_data[cur].A_W_0;
                  out_data[cnt].A_L_0 <= out_data[cur].A_L_0;
                  out_data[cnt].A_W_1 <= out_data[cur].A_W_1;
                  out_data[cnt].A_L_1 <= out_data[cur].A_L_0 + (((out_data[cur].A_L_1 - out_data[cur].A_L_0) + 1) >> 1) - 1;

                  out_data[cnt].B_W_0 <= out_data[cur].B_W_0;
                  out_data[cnt].B_L_0 <= out_data[cur].B_L_0;
                  out_data[cnt].B_W_1 <= out_data[cur].B_W_0 + ((out_data[cur].B_W_1 - out_data[cur].B_W_0 + 1) >> 1) - 1;
                  out_data[cnt].B_L_1 <= out_data[cur].B_L_1;
                  out_data[cur].to_n1 <= cnt;
                  out_data[cnt].O_W_0 <= out_data[cur].O_W_0;
                  out_data[cnt].O_L_0 <= out_data[cur].O_L_0;
                  out_data[cnt].O_W_1 <= out_data[cur].O_W_1;
                  out_data[cnt].O_L_1 <= out_data[cur].O_L_1;


                  out_data[cnt+1].A_W_0 <= out_data[cur].A_W_0;
                  out_data[cnt+1].A_L_0 <= out_data[cur].A_L_0 + (((out_data[cur].A_L_1 - out_data[cur].A_L_0) + 1) >> 1);
                  out_data[cnt+1].A_W_1 <= out_data[cur].A_W_1;
                  out_data[cnt+1].A_L_1 <= out_data[cur].A_L_1;

                  out_data[cnt+1].B_W_0 <= out_data[cur].B_W_0 + (((out_data[cur].B_W_1 - out_data[cur].B_W_0) + 1) >> 1);
                  out_data[cnt+1].B_L_0 <= out_data[cur].B_L_0;
                  out_data[cnt+1].B_W_1 <= out_data[cur].B_W_1;
                  out_data[cnt+1].B_L_1 <= out_data[cur].B_L_1;

                  out_data[cnt+1].O_W_0 <= out_data[cur].O_W_0;
                  out_data[cnt+1].O_L_0 <= out_data[cur].O_L_0;
                  out_data[cnt+1].O_W_1 <= out_data[cur].O_W_1;
                  out_data[cnt+1].O_L_1 <= out_data[cur].O_L_1;

                  out_data[cur].to_n2 <= cnt + 1;
                  cnt <= cnt + 2;
                end
              end
            end
            out_data[cnt].parent   <= cur;
            out_data[cnt+1].parent <= cur;
          end else begin
            if (first_none == 0) first_none <= cur;
          end
          cur <= cur + 1;

        end else begin
          ready <= 1'b1;
          last  <= cur;
        end
      end
    end
  end

endmodule

lab_14/src/01_mnist/01_HDL/02_sys_array_split/simulation/tb_sys_array_split.sv
`timescale 1 ns / 100 ps

`ifndef types
`define types 0;
typedef struct packed {
  logic [9:0] A_W_0, A_L_0, A_W_1, A_L_1;
  logic [9:0] B_W_0, B_L_0, B_W_1, B_L_1;
  logic [9:0] O_W_0, O_L_0, O_W_1, O_L_1;
  logic [7:0] to_n1;
  logic [7:0] to_n2;
  logic signed [8:0] parent;
} split_type;
`endif

module tb_sys_array_split #(
    parameter ARRAY_A_W = 5,  //Строк в массиве данных
    parameter ARRAY_A_L = 2,  //Столбцов в массиве данных
    parameter ARRAY_W_W = 2,  //Строк в массиве весов
    parameter ARRAY_W_L = 5,  //Столбцов в массиве весов    
    parameter ARRAY_W = 4, //Максимальное число строк в систолическом массиве
    parameter ARRAY_L = 4, //Максимальное число столбцов в систолическом массиве 
    parameter ARRAY_MAX_A_W = 4,
    parameter OUT_SIZE = 10
);


  reg clk, reset_n, ready, start;

  split_type out_data[OUT_SIZE];
  wire [7:0] first_none;
  wire [7:0] last;

  sys_array_split #(
      .ARRAY_W      (ARRAY_W),
      .ARRAY_L      (ARRAY_L),
      .ARRAY_MAX_A_W(ARRAY_MAX_A_W),
      .OUT_SIZE     (OUT_SIZE)
  ) systolic_array_split (
      .clk(clk),
      .reset_n(reset_n),
      .start(start),
      .ARRAY_W_W(ARRAY_W_W),
      .ARRAY_W_L(ARRAY_W_L),
      .ARRAY_A_W(ARRAY_A_W),
      .ARRAY_A_L(ARRAY_A_L),

      .ready(ready),
      .out_data(out_data),
      .first_none(first_none),
      .last(last)
  );

  initial $dumpvars;
  initial begin
    clk = 0;
    forever #10 clk = !clk;
  end

  initial begin
    reset_n = 0;
    start   = 0;
    #20;
    reset_n = 1;
    #20;
    start = 1;
    #20;
    start = 0;
    #20;
    while (!ready) begin
      #20;
    end
    $finish;
  end
endmodule

lab_14/src/01_mnist/01_HDL/02_sys_array_split/simulation/sim/dump.vcd
$date
	Sat Aug 10 13:04:52 2024
$end
$version
	ModelSim Version 10.5b
$end
$timescale
	100ps
$end

$scope module tb_sys_array_split $end
$var parameter 32 ! ARRAY_A_W $end
$var parameter 32 " ARRAY_A_L $end
$var parameter 32 # ARRAY_W_W $end
$var parameter 32 $ ARRAY_W_L $end
$var parameter 32 % ARRAY_W $end
$var parameter 32 & ARRAY_L $end
$var parameter 32 ' ARRAY_MAX_A_W $end
$var parameter 32 ( OUT_SIZE $end
$var reg 1 ) clk $end
$var reg 1 * reset_n $end
$var reg 1 + ready $end
$var reg 1 , start $end
$var wire 1 - first_none [7] $end
$var wire 1 . first_none [6] $end
$var wire 1 / first_none [5] $end
$var wire 1 0 first_none [4] $end
$var wire 1 1 first_none [3] $end
$var wire 1 2 first_none [2] $end
$var wire 1 3 first_none [1] $end
$var wire 1 4 first_none [0] $end
$var wire 1 5 last [7] $end
$var wire 1 6 last [6] $end
$var wire 1 7 last [5] $end
$var wire 1 8 last [4] $end
$var wire 1 9 last [3] $end
$var wire 1 : last [2] $end
$var wire 1 ; last [1] $end
$var wire 1 < last [0] $end

$scope module systolic_array_split $end
$var parameter 32 = ARRAY_W $end
$var parameter 32 > ARRAY_L $end
$var parameter 32 ? ARRAY_MAX_A_W $end
$var parameter 32 @ OUT_SIZE $end
$var wire 1 A clk $end
$var wire 1 B reset_n $end
$var wire 1 C start $end
$var wire 1 D ARRAY_W_W [9] $end
$var wire 1 E ARRAY_W_W [8] $end
$var wire 1 F ARRAY_W_W [7] $end
$var wire 1 G ARRAY_W_W [6] $end
$var wire 1 H ARRAY_W_W [5] $end
$var wire 1 I ARRAY_W_W [4] $end
$var wire 1 J ARRAY_W_W [3] $end
$var wire 1 K ARRAY_W_W [2] $end
$var wire 1 L ARRAY_W_W [1] $end
$var wire 1 M ARRAY_W_W [0] $end
$var wire 1 N ARRAY_W_L [9] $end
$var wire 1 O ARRAY_W_L [8] $end
$var wire 1 P ARRAY_W_L [7] $end
$var wire 1 Q ARRAY_W_L [6] $end
$var wire 1 R ARRAY_W_L [5] $end
$var wire 1 S ARRAY_W_L [4] $end
$var wire 1 T ARRAY_W_L [3] $end
$var wire 1 U ARRAY_W_L [2] $end
$var wire 1 V ARRAY_W_L [1] $end
$var wire 1 W ARRAY_W_L [0] $end
$var wire 1 X ARRAY_A_W [9] $end
$var wire 1 Y ARRAY_A_W [8] $end
$var wire 1 Z ARRAY_A_W [7] $end
$var wire 1 [ ARRAY_A_W [6] $end
$var wire 1 \ ARRAY_A_W [5] $end
$var wire 1 ] ARRAY_A_W [4] $end
$var wire 1 ^ ARRAY_A_W [3] $end
$var wire 1 _ ARRAY_A_W [2] $end
$var wire 1 ` ARRAY_A_W [1] $end
$var wire 1 a ARRAY_A_W [0] $end
$var wire 1 b ARRAY_A_L [9] $end
$var wire 1 c ARRAY_A_L [8] $end
$var wire 1 d ARRAY_A_L [7] $end
$var wire 1 e ARRAY_A_L [6] $end
$var wire 1 f ARRAY_A_L [5] $end
$var wire 1 g ARRAY_A_L [4] $end
$var wire 1 h ARRAY_A_L [3] $end
$var wire 1 i ARRAY_A_L [2] $end
$var wire 1 j ARRAY_A_L [1] $end
$var wire 1 k ARRAY_A_L [0] $end
$var reg 1 l ready $end
$var reg 8 m first_none [7:0] $end
$var reg 8 n last [7:0] $end
$var reg 10 o cnt [9:0] $end
$var reg 10 p cur [9:0] $end
$upscope $end
$upscope $end

$scope begin tb_sys_array_split_sv_unit $end
$upscope $end

$scope begin std $end
$upscope $end

$scope begin sys_array_split_sv_unit $end
$upscope $end
$enddefinitions $end
#0
$dumpvars
0)
0*
x+
0,
xl
bx m
bx n
bx o
bx p
b101 !
b10 "
b10 #
b101 $
b100 %
b100 &
b100 '
b1010 (
b100 =
b100 >
b100 ?
b1010 @
x4
x3
x2
x1
x0
x/
x.
x-
x<
x;
x:
x9
x8
x7
x6
x5
0A
0B
0C
0M
1L
0K
0J
0I
0H
0G
0F
0E
0D
1W
0V
1U
0T
0S
0R
0Q
0P
0O
0N
1a
0`
1_
0^
0]
0\
0[
0Z
0Y
0X
0k
1j
0i
0h
0g
0f
0e
0d
0c
0b
$end
#100
1)
1A
b0 o
b0 p
0l
b0 n
b0 m
0+
04
03
02
01
00
0/
0.
0-
0<
0;
0:
09
08
07
06
05
#200
1*
0)
1B
0A
#300
1)
1A
b1 o
#400
1,
0)
1C
0A
#500
1)
1A
b0 o
#600
0,
0)
0C
0A
#700
1)
1A
b1 o
#800
0)
0A
#900
1)
1A
b11 o
b1 p
#1000
0)
0A
#1100
1)
1A
b101 o
b10 p
#1200
0)
0A
#1300
1)
1A
b111 o
b11 p
#1400
0)
0A
#1500
1)
1A
b11 m
b100 p
14
13
#1600
0)
0A
#1700
1)
1A
b101 p
#1800
0)
0A
#1900
1)
1A
b110 p
#2000
0)
0A
#2100
1)
1A
b111 p
#2200
0)
0A
#2300
1)
1A
1l
b111 n
1+
1<
1;
1:
